com/__init__.py
com/inductiveautomation/__init__.py
com/inductiveautomation/factorypmi/__init__.py
com/inductiveautomation/factorypmi/application/__init__.py
com/inductiveautomation/factorypmi/application/script/__init__.py
com/inductiveautomation/factorypmi/application/script/builtin/__init__.py
com/inductiveautomation/ignition/__init__.py
com/inductiveautomation/ignition/client/__init__.py
com/inductiveautomation/ignition/client/util/__init__.py
com/inductiveautomation/ignition/client/util/gui/__init__.py
com/inductiveautomation/ignition/client/util/gui/scheduling/__init__.py
com/inductiveautomation/ignition/common/__init__.py
com/inductiveautomation/ignition/common/alarming/__init__.py
com/inductiveautomation/ignition/common/alarming/evaluation/__init__.py
com/inductiveautomation/ignition/common/alarming/query/__init__.py
com/inductiveautomation/ignition/common/browsing/__init__.py
com/inductiveautomation/ignition/common/messages/__init__.py
com/inductiveautomation/ignition/common/model/__init__.py
com/inductiveautomation/ignition/common/model/values/__init__.py
com/inductiveautomation/ignition/common/script/__init__.py
com/inductiveautomation/ignition/common/script/abc/__init__.py
com/inductiveautomation/ignition/common/script/adapters/__init__.py
com/inductiveautomation/ignition/common/script/builtin/__init__.py
com/inductiveautomation/ignition/common/script/builtin/http/__init__.py
com/inductiveautomation/ignition/common/script/builtin/ialabs/__init__.py
com/inductiveautomation/ignition/common/script/message/__init__.py
com/inductiveautomation/ignition/common/sqltags/__init__.py
com/inductiveautomation/ignition/common/sqltags/history/__init__.py
com/inductiveautomation/ignition/common/user/__init__.py
com/inductiveautomation/ignition/common/user/schedule/__init__.py
com/inductiveautomation/ignition/common/util/__init__.py
com/inductiveautomation/ignition/modules/__init__.py
com/inductiveautomation/ignition/modules/serial/__init__.py
ignition_api_jython-8.1.10.post3.dist-info/LICENSE
ignition_api_jython-8.1.10.post3.dist-info/METADATA
ignition_api_jython-8.1.10.post3.dist-info/WHEEL
ignition_api_jython-8.1.10.post3.dist-info/top_level.txt
ignition_api_jython-8.1.10.post3.dist-info/RECORD
