Metadata-Version: 2.1
Name: ignition-api-jython
Version: 8.1.10.post3
Summary: Ignition Scripting API.
Home-page: https://github.com/thecesrom/Ignition/tree/jython
Author: César Román
Author-email: cesar@thecesrom.dev
License: MIT
Keywords: hmi,ignition,inductive automation,scada
Platform: UNKNOWN
Classifier: Development Status :: 7 - Inactive
Classifier: Intended Audience :: Developers
Classifier: Intended Audience :: Information Technology
Classifier: Intended Audience :: Manufacturing
Classifier: License :: OSI Approved :: MIT License
Classifier: Operating System :: MacOS :: MacOS X
Classifier: Operating System :: Microsoft :: Windows
Classifier: Operating System :: POSIX :: Linux
Classifier: Programming Language :: Python
Classifier: Programming Language :: Python :: 2
Classifier: Programming Language :: Python :: Implementation
Classifier: Programming Language :: Python :: Implementation :: Jython
Classifier: Topic :: Software Development :: Libraries :: Python Modules
Classifier: Topic :: Software Development :: Testing :: Mocking
